GreenPonik_BME280/BME280.py
GreenPonik_BME280/__init__.py
tests/__init__.py
tests/test_BME280.py
greenponik_bme280-0.0.5.dist-info/METADATA
greenponik_bme280-0.0.5.dist-info/WHEEL
greenponik_bme280-0.0.5.dist-info/top_level.txt
greenponik_bme280-0.0.5.dist-info/RECORD
