Metadata-Version: 2.1
Name: greenponik-bme280
Version: 0.0.5
Summary: Read BM280 through Python3 on raspberry pi
Home-page: https://github.com/GreenPonik/GreenPonik_BM280
Author: GreenPonik SAS
Author-email: contact@greenponik.com
License: MIT
Project-URL: Source, https://github.com/GreenPonik/GreenPonik_BM280/
Project-URL: Bug Reports, https://github.com/GreenPonik/GreenPonik_BM280/issues
Keywords: GreenPonik hydroponics bme280     light reader python hardware diy iot raspberry pi
Platform: UNKNOWN
Classifier: Programming Language :: Python :: 3
Classifier: License :: OSI Approved :: MIT License
Classifier: Operating System :: OS Independent
Requires-Python: >=3.6.0
Requires-Dist: adafruit-blinka
Requires-Dist: adafruit-circuitpython-bme280
Requires-Dist: adafruit-extended-bus
